accretion_common/__init__.py
accretion_common/constants.py
accretion_common/exceptions.py
accretion_common/util.py
accretion_common/venv_magic/__init__.py
accretion_common/venv_magic/builder.py
accretion_common/venv_magic/uploader.py
accretion_common/venv_magic/zipper.py
accretion_common-0.1.1.data/data/CHANGELOG.rst
accretion_common-0.1.1.data/data/LICENSE
accretion_common-0.1.1.data/data/README.rst
accretion_common-0.1.1.data/data/requirements.txt
accretion_common-0.1.1.dist-info/LICENSE
accretion_common-0.1.1.dist-info/METADATA
accretion_common-0.1.1.dist-info/WHEEL
accretion_common-0.1.1.dist-info/top_level.txt
accretion_common-0.1.1.dist-info/RECORD
