Metadata-Version: 2.1
Name: accretion-common
Version: 0.1.1
Summary: Common resources for Accretion components.
Home-page: https://github.com/mattsb42/accretion
Author: Matt Bullock
Author-email: m@ttsb42.com
Maintainer: Matt Bullock
License: Apache 2.0
Keywords: accretion_common accretion_common
Platform: UNKNOWN
Classifier: Development Status :: 4 - Beta
Classifier: Intended Audience :: Developers
Classifier: Natural Language :: English
Classifier: License :: OSI Approved :: Apache Software License
Classifier: Programming Language :: Python
Classifier: Programming Language :: Python :: 3
Classifier: Programming Language :: Python :: 3.6
Classifier: Programming Language :: Python :: 3.7
Classifier: Programming Language :: Python :: Implementation :: CPython
Requires-Dist: boto3
Requires-Dist: attrs (>=19.1.0)
Requires-Dist: setuptools
